{"project_info":{"project_id":"android-wear-demo","project_number":"341498350951","name":"Android Wear Demo"},"client":[{"client_info":{"client_id":"android:mx.softux.androidweardemo","client_type":1,"android_client_info":{"package_name":"mx.softux.androidweardemo"}},"oauth_client":[],"services":{"analytics_service":{"status":1},"cloud_messaging_service":{"status":2,"apns_config":[]},"appinvite_service":{"status":1,"other_platform_oauth_client":[]},"google_signin_service":{"status":1},"ads_service":{"status":1}}}]}